tpu_index/__init__.py
tpu_index/index.py
tpu_index-0.0.6.dist-info/METADATA
tpu_index-0.0.6.dist-info/WHEEL
tpu_index-0.0.6.dist-info/top_level.txt
tpu_index-0.0.6.dist-info/RECORD
