Metadata-Version: 2.1
Name: tpu-index
Version: 0.0.6
Summary: TPU index is a package for fast similarity search over large collections of high dimension vectors on Google Cloud TPUs
Home-page: https://github.com/srihari-humbarwadi/tpu_index
Author: Srihari Humbarwadi
Author-email: sriharihumbarwadi97@gmail.com
License: UNKNOWN
Platform: UNKNOWN
Classifier: Programming Language :: Python :: 3
Classifier: License :: OSI Approved :: MIT License
Classifier: Operating System :: OS Independent
Requires-Python: >=3.5
Requires-Dist: tensorflow (>=2.0.0)
